nonebot_plugin_running_state/__init__.py
nonebot_plugin_running_state-0.0.6.dist-info/METADATA
nonebot_plugin_running_state-0.0.6.dist-info/WHEEL
nonebot_plugin_running_state-0.0.6.dist-info/top_level.txt
nonebot_plugin_running_state-0.0.6.dist-info/RECORD
