Metadata-Version: 2.1
Name: nonebot-plugin-running-state
Version: 0.0.6
Summary: 基于 nonebot2和Lagrange.OneBot 的运行状态插件
Author-email: zhongwen-4 <2401128923@qq.com>
License: AGPL3.0
Requires-Python: >=3.10.0
Requires-Dist: nonebot2 >=2.3.3
Requires-Dist: nonebot-adapter-onebot >=2.4.5
Requires-Dist: psutil >=6.0.0
Requires-Dist: nonebot-plugin-localstore >=0.7.1
